{
  "アルク": "alk",
  "シロ": "white_tiger",
  "ヴァーグナー": "fire_dragon",
  "マリーナ": "pirates_girl",
  "クラリス": "clarisse",
  "ソーニャ": "brown_fighter",
  "スイゼン": "onmyoji_boy",
  "イナホ": "fox_oracle",
  "カリオストロ": "cagliostro",
  "シルティー": "wind_spgirl",
  "フィリア": "wind_oracle",
  "ムラクモ": "katana_ghost",
  "レオン": "mercenary",
  "ネフティム": "ruin_girl",
  "ラーゼルト": "prince_zero",
  "エクリール": "bodysuit_trooper",
  "ベルセティア": "dimension_witch",
  "ヴェロン": "veteran_hunter",
  "アゼル": "dragon_slayer",
  "ビアンカ": "lady_summoner",
  "ハナビ": "kunoichi",
  "アスキリマル": "half_oni_boy",
  "グライド": "master_knight",
  "ユーウェル": "swallow_knight",
  "リーゼル": "bishop_girl",
  "アメリア": "mermaid",
  "アリス": "alice",
  "シャロン": "battle_guild_staff",
  "ラナー": "spry_sailor",
  "ラムス": "thunder_dragon",
  "ルナール": "fox_scientist",
  "レジス": "rec_android",
  "エレンノール": "elf_soldier",
  "ジェイ": "cat_shaman",
  "ミノ": "minotaur_girl",
  "ミア": "tiger_treasure_hunter",
  "オロウル": "birdman",
  "ソウシロウ": "samurai",
  "メルスール": "elf_archer",
  "ヘルガ": "dog_slasher",
  "アリサ": "arisa",
  "ディア": "sing_android",
  "ジェラール": "unicorn_lancer",
  "エリヤ": "lightbullet_wiz",
  "フィン": "palpebra_knight",
  "キーラ": "palpebra_knight_lady",
  "アルム": "devil_princess",
  "マリアンネ": "battle_maid",
  "アンディ": "undead_boy",
  "リアン": "warlock",
  "リリル": "alchemist",
  "メイミー": "pretty_witch",
  "イリス": "gunslinger",
  "ハーシュ": "monster_hunter",
  "ジン": "black_doctor",
  "トレーネ": "cool_woman_soldier",
  "ギルスラッド": "berserker",
  "エンニ": "fire_shaman",
  "ジェイク": "disciplined_swordman",
  "ケイロス": "sniper",
  "トリスタ": "urban_soldier",
  "ヴァルター": "hard_face_soldier",
  "エルザ": "nurse",
  "クラウス": "wolf_assassin",
  "シラノ": "fox_companion",
  "カイユ": "depraved_monk",
  "ラッティ": "sailor_girl",
  "ファフ": "cute_fafnir",
  "リコ": "mens_attire_girl",
  "ユナ": "twin_blader",
  "ホーニィ": "bee_girl",
  "タイガ": "lightning_fighter",
  "クロ": "outlaw_panther",
  "アルベルト": "wolf_swordsman",
  "カヅチ": "oni_girl",
  "タチアナ": "sociable_mestizo",
  "コルト": "magic_boy",
  "シャ・スス": "student_gunsmith",
  "エヴァン": "highlander",
  "チャルア": "dryad",
  "レシタール": "lich",
  "ネスカ": "casino_dealer",
  "ミュウ": "cat_fighter",
  "フォルス": "devil_clown",
  "ハートリーフ": "herbalist",
  "コナー": "spearman",
  "ジャスター": "trap_errand",
  "コリーナ": "priest",
  "マルグリット": "lady_gunner",
  "セシリア": "woman_knight",
  "アウレオ": "docking_beast",
  "ラウル": "exorcist_oldman",
  "ミレス": "half_knight",
  "リュリュカ": "reporter",
  "ファルチェ": "reaper_girl",
  "ジャリル": "chakram_shooter",
  "アーリィ": "devil_woman_soldier",
  "シオン": "informant",
  "アディル": "arabic_swordman",
  "ドロセア": "dark_nursemaid",
  "レベッカ": "bearish_darkwitch",
  "ゴーレム": "guardian_golem",
  "ポジート": "owl",
  "カマイタチ": "fox",
  "キノ": "kinoko",
  "レッドプル": "slango_red",
  "ファイアスピリ": "spirit_fire",
  "ブループル": "slango_blue",
  "イエロープル": "slango_yellow",
  "パララット": "paralysis_hedgehog",
  "グリーンプル": "slango_green"
}